robopom/ComponentVariables.py
robopom/RobopomPage.py
robopom/RobopomSeleniumPlugin.py
robopom/__init__.py
robopom/component_loader.py
robopom/constants.py
robopom/model.py
robopom/cli/__init__.py
robopom/cli/cli.py
robopom/cli/robopom.py
robopom/cli/template.py
robopom/resources/__init__.py
robopom/resources/template_files/README_-_md
robopom/resources/template_files/_-_gitignore
robopom/resources/template_files/__init__.py
robopom/resources/template_files/_dot_project_sample
robopom/resources/template_files/argumentfile
robopom/resources/template_files/doc__--RobopomPageDoc_-_html
robopom/resources/template_files/doc__--SeleniumRobopomPluginDoc_-_html
robopom/resources/template_files/node_modules__--dictionary-es__--index_-_aff
robopom/resources/template_files/node_modules__--dictionary-es__--index_-_dic
robopom/resources/template_files/node_modules__--dictionary-es__--index_-_js
robopom/resources/template_files/node_modules__--dictionary-es__--license
robopom/resources/template_files/node_modules__--dictionary-es__--package_-_json
robopom/resources/template_files/node_modules__--dictionary-es__--readme_-_md
robopom/resources/template_files/pages__--mtp__--mtp_home_page_-_resource
robopom/resources/template_files/pages__--mtp__--mtp_home_page_-_yaml
robopom/resources/template_files/pages__--mtp__--mtp_page_-_resource
robopom/resources/template_files/pages__--mtp__--mtp_page_-_yaml
robopom/resources/template_files/pages__--mtp__--mtp_search_results_page_-_resource
robopom/resources/template_files/pages__--mtp__--mtp_search_results_page_-_yaml
robopom/resources/template_files/pages__--omnia__--account__--omnia_account_page_-_resource
robopom/resources/template_files/pages__--omnia__--account__--omnia_account_page_-_yaml
robopom/resources/template_files/pages__--omnia__--omnia_login_page_-_resource
robopom/resources/template_files/pages__--omnia__--omnia_login_page_-_yaml
robopom/resources/template_files/pages__--omnia__--omnia_main_page_-_resource
robopom-0.1.0.dist-info/LICENSE
robopom-0.1.0.dist-info/METADATA
robopom-0.1.0.dist-info/WHEEL
robopom-0.1.0.dist-info/entry_points.txt
robopom-0.1.0.dist-info/top_level.txt
robopom-0.1.0.dist-info/RECORD
